odoo/addons/crm_helpdesk/README.rst
odoo/addons/crm_helpdesk/__init__.py
odoo/addons/crm_helpdesk/__manifest__.py
odoo/addons/crm_helpdesk/demo/crm_helpdesk_demo.xml
odoo/addons/crm_helpdesk/i18n/af.po
odoo/addons/crm_helpdesk/i18n/am.po
odoo/addons/crm_helpdesk/i18n/ar.po
odoo/addons/crm_helpdesk/i18n/bg.po
odoo/addons/crm_helpdesk/i18n/bs.po
odoo/addons/crm_helpdesk/i18n/ca.po
odoo/addons/crm_helpdesk/i18n/crm_helpdesk.pot
odoo/addons/crm_helpdesk/i18n/cs.po
odoo/addons/crm_helpdesk/i18n/da.po
odoo/addons/crm_helpdesk/i18n/de.po
odoo/addons/crm_helpdesk/i18n/el.po
odoo/addons/crm_helpdesk/i18n/en_GB.po
odoo/addons/crm_helpdesk/i18n/es.po
odoo/addons/crm_helpdesk/i18n/es_AR.po
odoo/addons/crm_helpdesk/i18n/es_BO.po
odoo/addons/crm_helpdesk/i18n/es_CL.po
odoo/addons/crm_helpdesk/i18n/es_CO.po
odoo/addons/crm_helpdesk/i18n/es_CR.po
odoo/addons/crm_helpdesk/i18n/es_DO.po
odoo/addons/crm_helpdesk/i18n/es_EC.po
odoo/addons/crm_helpdesk/i18n/es_MX.po
odoo/addons/crm_helpdesk/i18n/es_PE.po
odoo/addons/crm_helpdesk/i18n/es_PY.po
odoo/addons/crm_helpdesk/i18n/es_VE.po
odoo/addons/crm_helpdesk/i18n/et.po
odoo/addons/crm_helpdesk/i18n/eu.po
odoo/addons/crm_helpdesk/i18n/fa.po
odoo/addons/crm_helpdesk/i18n/fi.po
odoo/addons/crm_helpdesk/i18n/fr.po
odoo/addons/crm_helpdesk/i18n/fr_BE.po
odoo/addons/crm_helpdesk/i18n/fr_CA.po
odoo/addons/crm_helpdesk/i18n/gl.po
odoo/addons/crm_helpdesk/i18n/gu.po
odoo/addons/crm_helpdesk/i18n/he.po
odoo/addons/crm_helpdesk/i18n/hi.po
odoo/addons/crm_helpdesk/i18n/hr.po
odoo/addons/crm_helpdesk/i18n/hu.po
odoo/addons/crm_helpdesk/i18n/hy.po
odoo/addons/crm_helpdesk/i18n/id.po
odoo/addons/crm_helpdesk/i18n/is.po
odoo/addons/crm_helpdesk/i18n/it.po
odoo/addons/crm_helpdesk/i18n/ja.po
odoo/addons/crm_helpdesk/i18n/ka.po
odoo/addons/crm_helpdesk/i18n/kab.po
odoo/addons/crm_helpdesk/i18n/kk.po
odoo/addons/crm_helpdesk/i18n/ko.po
odoo/addons/crm_helpdesk/i18n/lo.po
odoo/addons/crm_helpdesk/i18n/lt.po
odoo/addons/crm_helpdesk/i18n/lv.po
odoo11_addon_crm_helpdesk-11.0.1.0.0.99.dev15.dist-info/METADATA
odoo11_addon_crm_helpdesk-11.0.1.0.0.99.dev15.dist-info/WHEEL
odoo11_addon_crm_helpdesk-11.0.1.0.0.99.dev15.dist-info/top_level.txt
odoo11_addon_crm_helpdesk-11.0.1.0.0.99.dev15.dist-info/RECORD
